{"type":"FeatureCollection","features": [
    {
        "type":"Feature",
        "properties": {
            "scalerank":0,
            "natscale":600,
            "labelrank":3,
            "featurecla":"Admin-1 capital",
            "name":"Sydney",
            "namepar":null,
            "namealt":null,
            "diffascii":0,
            "nameascii":"Sydney",
            "adm0cap":0,
            "capalt":null,
            "capin":null,
            "worldcity":1,
            "megacity":1,
            "sov0name":"Australia",
            "sov_a3":"AUS",
            "adm0name":"Australia",
            "adm0_a3":"AUS",
            "adm1name":"New South Wales",
            "iso_a2":"AU",
            "note":null,
            "latitude":-33.9200109672,
            "longitude":151.185179809,
            "changed":4,
            "namediff":0,
            "diffnote":"Changed feature class.",
            "pop_max":8630000,
            "pop_min":3641422,
            "pop_other":2669348,
            "rank_max":12,
            "rank_min":12,
            "geonameid":2147714,
            "meganame":"Sydney",
            "ls_name":"Sydney1",
            "ls_match":1,
            "checkme":0,
            "min_zoom":1.7
        },
        "bbox":[151.183234,-33.918065,151.183234,-33.918065],
        "geometry":{
            "type":"Point",
            "coordinates":[151.183234,-33.918065]
        }
    },
    {
        "type":"Feature",
        "properties":{
            "scalerank":1,
            "natscale":300,
            "labelrank":3,
            "featurecla":"Admin-1 capital",
            "name":"Melbourne",
            "namepar":null,
            "namealt":null,
            "diffascii":0,
            "nameascii":"Melbourne",
            "adm0cap":0,
            "capalt":null,
            "capin":null,
            "worldcity":1,
            "megacity":1,
            "sov0name":"Australia",
            "sov_a3":"AUS",
            "adm0name":"Australia",
            "adm0_a3":"AUS",
            "adm1name":"Victoria",
            "iso_a2":"AU",
            "note":null,
            "latitude":-37.8200313123,
            "longitude":144.975016235,
            "changed":4,
            "namediff":0,
            "diffnote":"Changed feature class. Changed scale rank.",
            "pop_max":4170000,
            "pop_min":93625,
            "pop_other":1805353,
            "rank_max":12,
            "rank_min":8,
            "geonameid":2158177,
            "meganame":"Melbourne",
            "ls_name":"Melbourne2",
            "ls_match":1,
            "checkme":0,
            "min_zoom":3
        },
        "bbox":[144.97307,-37.818085,144.97307,-37.818085],
        "geometry":{
            "type":"Point",
            "coordinates":[144.97307,-37.818085]
            }
        },
        {
            "type":"Feature",
            "properties":{
                "scalerank":1,
                "natscale":200,
                "labelrank":7,
                "featurecla":"Admin-1 capital",
                "name":"Perth",
                "namepar":null,
                "namealt":null,
                "diffascii":0,
                "nameascii":"Perth",
                "adm0cap":0,
                "capalt":null,
                "capin":null,
                "worldcity":1,
                "megacity":1,
                "sov0name":"Australia",
                "sov_a3":"AUS",
                "adm0name":"Australia",
                "adm0_a3":"AUS",
                "adm1name":"Western Australia",
                "iso_a2":"AU",
                "note":null,
                "latitude":-31.953512,
                "longitude":115.857048,
                "changed":4,
                "namediff":0,
                "diffnote":"Changed feature class. Changed scale rank.",
                "pop_max":4170000,
                "pop_min":93625,
                "pop_other":1805353,
                "rank_max":12,
                "rank_min":8,
                "geonameid":32158177,
                "meganame":"Perth",
                "ls_name":"Perth2",
                "ls_match":1,
                "checkme":0,
                "min_zoom":3
            },
            "bbox":[115.857048,-31.953512,115.857048,-31.953512],
            "geometry":{
                "type":"Point",
                "coordinates":[115.857048,-31.953512]
                }
            }
    ]}